protoss/__init__.py
protoss/coordination.py
protoss-0.0.1.dist-info/METADATA
protoss-0.0.1.dist-info/WHEEL
protoss-0.0.1.dist-info/RECORD
