Metadata-Version: 2.3
Name: protoss
Version: 0.0.1
Summary: Distributed AI coordination architecture. Ephemeral agent swarms with democratic oversight.
License: MIT
Keywords: ai,agents,protoss,coordination,distributed,cognition,autonomous,multiagent,starcraft,psionic
Author: Tyson Chan
Author-email: tyson.chan@proton.me
Requires-Python: >=3.9,<4.0
Classifier: Development Status :: 3 - Alpha
Classifier: Intended Audience :: Developers
Classifier: Topic :: Software Development :: Libraries :: Python Modules
Classifier: Topic :: Scientific/Engineering :: Artificial Intelligence
Classifier: License :: OSI Approved :: MIT License
Classifier: Programming Language :: Python :: 3
Classifier: Programming Language :: Python :: 3.9
Classifier: Programming Language :: Python :: 3.10
Classifier: Programming Language :: Python :: 3.11
Classifier: Programming Language :: Python :: 3.12
Requires-Dist: asyncio-mqtt (>=0.13.0)
Requires-Dist: cogency (>=0.3.0)
Requires-Dist: websockets (>=12.0)
